{
  "navigation": {
    "homepage": "Home",
    "analysis": "Analysis",
    "logout": "Logout",
    "logoutFailed": "Logout failed.",
    "configLoadingError": "An error occured while loading the UI configurations"
  },
  "login": {
    "username": "Username",
    "password": "Password",
    "btn": "Login",
    "error": "An error occurred. Could not log you in."
  },
  "footer": {
    "importing": "is importing...",
    "connected": "is connected",
    "notConnected": "is not connected",
    "rightsReserved": "All Rights Reserved"
  },
  "license": {
    "licensedFor": "Licensed for",
    "validUntil": "Valid until",
    "redirectMessage": "You will be redirected to login page shortly. <a href=\"./\">Click here to go to login page immediately</a>",
    "licenseKey": "License Key",
    "enterLicense": "Please enter license key",
    "submit": "Submit"
  },
  "home": {
    "createBtn": {
      "default": "Create New",
      "collection": "New Collection",
      "dashboard": "New Dashboard",
      "report": {
        "default": "New Report",
        "process": "Process Report",
        "combined": "Combined Process Report",
        "decision": "Decision Report"
      }
    },
    "title": "Collections, Dashboards, and Reports",
    "search": {
      "name": "Filter for name...",
      "id": "Filter for user ID..."
    },
    "collectionTitle": "Dashboards and Reports",
    "collectionTitleWithAmpersand": "Dashboards & Reports",
    "userTitle": "Users and User Groups",
    "copy": {
      "subEntity": "This {entityType} contains 1 Report. It will be copied, too.",
      "subEntities": "This {entityType} contains {number} Reports. They will be copied, too.",
      "inputLabel": "Name of Copy",
      "moveLabel": "Move copy to …",
      "noCollections": "No collections have been created",
      "pleaseSelect": "Please select",
      "gotoNew": "Go to new location"
    },
    "types": {
      "process": "Process Report",
      "decision": "Decision Report",
      "combined": "Combined Report",
      "unknown": "Unknown Entity"
    },
    "roles": {
      "addUserTitle": "Add User or User Group",
      "userRole": "User role",
      "viewer": "Viewer",
      "viewer-description": "Read-only access to all objects",
      "editor": "Editor",
      "editor-description": "Create, edit and delete Dashboards and Reports",
      "manager": "Manager",
      "manager-description": "Full rights editing Collection and Users"
    },
    "data-hint": "Do you miss any data? The last update introduced user permissions. Ask your administrator for access rights.",
    "empty": "There are no items created yet",
    "notFound": "No results found"
  },
  "report": {
    "label": "Report",
    "label-plural": "Reports",
    "new": "New Report",
    "cannotSave": "Report \"{name}\" could not be saved",
    "downloadCSV": "Download CSV",
    "incomplete": "Showing {count} data points in the result. To refine the set of results, edit your set-up above.",
    "view": {
      "label": "View",
      "rawData": "Raw Data",
      "pi": "Process Instance",
      "fn": "Flow Node",
      "userTask": "User Task",
      "count": "Count",
      "duration": "Duration",
      "evaluationCount": "Evaluation Count"
    },
    "groupBy": {
      "label": "Group By",
      "none": "None",
      "flowNodes": "Flow Nodes",
      "startDate": "Start Date of Process Instance",
      "automatic": "Automatic",
      "endDate": "End Date of Process Instance",
      "variable": "Variable",
      "userAssignee": "Assignee",
      "userGroup": "Candidate Group",
      "evaluationDate": "Evaluation Date",
      "rules": "Rules",
      "inputVariable": "Input Variable",
      "outputVariable": "Output Variable",
      "year": "Year",
      "month": "Month",
      "week": "Week",
      "day": "Day",
      "hour": "Hour"
    },
    "visualization": {
      "label": "Visualization",
      "number": "Number",
      "bar": "Bar Chart",
      "line": "Line Chart",
      "pie": "Pie Chart",
      "table": "Table",
      "heat": "Heatmap"
    },
    "processPart": {
      "label": "Process Instance Part",
      "title": "Set Process Instance Part",
      "description": "Only regard part between",
      "selectStart": "Select start",
      "selectEnd": "Select end",
      "noPathWarning": "You selected two nodes, but there is no obvious connection between those nodes. Report results may be empty or misleading."
    },
    "heatTarget": {
      "label": "Target Value",
      "title": "Target Value Comparison",
      "table": {
        "activity": "Activity",
        "value": "Actual Value",
        "target": "Target Value"
      },
      "noChangeWarning": "Please change at least one value",
      "invalidValue": "All fields should have a numeric value",
      "targetDuration": "target duration",
      "actualDuration": "actual duration: {duration}<br/>{percentage}% of the target value",
      "noValueAvailable": "No actual value available.<br/>Cannot compare target and actual value."
    },
    "invalidCominationError": "Cannot display data for the given report settings. Please choose another combination!",
    "noDataNotice": "No data to display",
    "editSetupMessage": "To display this report, edit your set-up above.",
    "incompleteNotice": {
      "message": "To display this Report,",
      "action": "complete set-up…"
    },
    "setupNotice": "Set-up your Report",
    "editReportMessage": "<p>Select the <b>Edit</b> button above.</p>",
    "totalCount": {
      "instance": "Total Instance</br> Count: <b>{count}</b>",
      "evaluation": "Total Evaluation</br> Count: <b>{count}</b>"
    },
    "definition": {
      "process": "Process Definition",
      "decision": "Decision Defintion"
    },
    "noDefintionMessage": {
      "process": "Select a <b>Process Definition</b> above.",
      "decision": "Select a <b>Decision Definition</b> above."
    },
    "combinedEmptyMessage": "To display a report, please select one or more reports from the list.",
    "noViewMessage": "Select an option for <b>View</b> above.",
    "noGroupByMessage": "Select what to <b>Group By</b> above.",
    "noVisualizationMessage": "Select an option for <b>Visualization</b> above.",
    "variables": {
      "default": "Variables",
      "input": "Input Variables",
      "output": "Output Variables"
    },
    "table": {
      "noData": {
        "head": "No Data",
        "body": "You need to enable at least one table column"
      },
      "relativeFrequency": "Relative Frequency "
    },
    "progressBar": {
      "invalid": "Invalid Configuration",
      "goal": "Goal"
    },
    "combined": {
      "multiSelect": {
        "available": "Available reports",
        "selected": "Selected reports",
        "search": "Search for reports",
        "empty": "No reports found"
      }
    },
    "config": {
      "buttonTooltip": "Configuration Options",
      "reset": "Reset to Defaults",
      "showCount": {
        "instance": "Show Instance Count",
        "evaluation": "Show Evaluation Count"
      },
      "aggregation": {
        "legend": "Aggregation",
        "minimum": "Minimum",
        "average": "Average",
        "median": "Median",
        "maximum": "Maximum"
      },
      "userTaskDuration": {
        "legend": "User Task Duration Time",
        "idle": "Idle",
        "work": "Work",
        "total": "Total"
      },
      "userTaskDistributedBy": "Distributed By",
      "nodeStatus": {
        "legend": "Flow Node Status",
        "running": "Running",
        "completed": "Completed"
      },
      "visibleNodes": {
        "legend": "Customize Node Display",
        "btn": "Select Flow Nodes...",
        "modal": {
          "title": "Select Flow Nodes",
          "description": "Selected nodes appear in the visualization."
        }
      },
      "colorPicker": {
        "legend": "Color"
      },
      "tooltips": {
        "legend": "Tooltips",
        "showRelative": "Show Relative Value",
        "showAbsolute": "Show Absolute Value"
      },
      "axisLabels": {
        "legend": "Axis Labels",
        "xAxis": "X Axis Label",
        "yAxis": "Y Axis Label"
      },
      "goal": {
        "legend": "Goal",
        "goalValue": "Goal value",
        "baseline": "Baseline",
        "target": "Target",
        "invalidInput": "Must be a non-negative number",
        "lessThanTargetError": "Target must be greater than baseline"
      },
      "pointMarkers": {
        "legend": "Line points",
        "disableMarkers": "Disable point markers"
      },
      "limitPrecision": {
        "legend": "Limit Precision",
        "numberOf": {
          "digits": "No. of digits",
          "units": "No. of units"
        }
      },
      "includeTableColumn": "Table columns to include",
      "showGradientBars": "Show Gradient Bars"
    },
    "missingVariableValue": "null / undefined"
  },
  "dashboard": {
    "label": "Dashboard",
    "label-plural": "Dashboards",
    "new": "New Dashboard",
    "cannotSave": "Dashboard \"{name}\" could not be saved",
    "cannotShare": "You are not authorized to share the dashboard, because you don't have access to all reports on the dashboard!",
    "toggleTheme": "Toggle Theme",
    "enterFullscreen": "Enter Fullscreen",
    "leaveFullscreen": "Leave Fullscreen",
    "autoRefresh": "Auto Refresh",
    "addButton": {
      "addReport": "Add a Report",
      "selectReport": "Select Report",
      "addExternal": "Add External Source",
      "addReportLabel": "Add Report",
      "selectReportPlaceholder": "Select a Report",
      "noReports": "No reports have been created",
      "externalUrl": "External URL"
    }
  },
  "alert": {
    "label": "Alert",
    "label-plural": "Alerts",
    "createNew": "Create New Alert",
    "newAlert": "New Alert",
    "edit": "Edit Alert",
    "delete": "Delete Alert",
    "description": "Alert <span>{email}</span> when Report <span>{name}</span> has a value <span>{aboveOrBelow} {thresholdValue}</span>",
    "emailWarning": "The email notification service is not configured. Optimize won't be able to inform you about critical values. Please check out the <a href='{docsLink}'>Optimize documentation</a> on how to enable the notification service.",
    "form": {
      "name": "Alert Name",
      "report": "When Report",
      "reportPlaceholder": "Select a Report",
      "noReports": "No number reports have been created",
      "reportInfo": "Alerts only available for reports visualised as numbers",
      "threshold": "Has a Value",
      "frequency": "Check Report Every",
      "email": "Send Email to",
      "emailPlaceholder": "Email address",
      "sendNotification": "Send notification when resolved",
      "reminder": "Send reminder notification",
      "reminderFrequency": "every"
    },
    "apply": "Apply Changes",
    "create": "Create Alert",
    "cannotSave": "Alert \"{name}\" could not be saved."
  },
  "analysis": {
    "branchAnalysis": "Branch Analysis",
    "outlier": {
      "label": "Outlier Analysis",
      "totalInstances": "Total Instances",
      "tooltip": {
        "outlier": {
          "label": "Outlier",
          "label-plural": "Outliers"
        },
        "instance": {
          "label": "instance",
          "label-plural": "instances"
        },
        "tookDuration": "Took a duration of"
      },
      "onlyCompletedHint": "Note: The outlier analysis is only performed on completed flow nodes only",
      "info": "Heatmap displays the incidence of higher outliers based on duration. Calculated by z-score.",
      "tooltipText": "{count} {instance} took {percentage}% longer than average.",
      "detailsModal": {
        "title": "Outliers of {name} Flow Node",
        "durationChart": "Duration Distribution chart",
        "variablesTable": "Common Significant Variables Table",
        "axisLabels": {
          "duration": "Duration",
          "instanceCount": "Instance Count"
        },
        "table": {
          "emptyTableMessage": "No significant variable value occurrences found on outlier instances",
          "outliersNumber": "Number of Outlier Instances",
          "ofTotalPercentage": "% of Total Instances",
          "ofOutliersPercentage": "% of Outlier Instances"
        }
      }
    },
    "selectLabel": "For",
    "gatwayLabel": "analyse how the branches of",
    "endEventLabel": "affect the probability that an instance reached",
    "emptySelectionLabel": {
      "gateway": "Select Gateway",
      "endEvent": "Select End Event"
    },
    "instructionMessage": "Please select a Process Definition, a Gateway and an End Event to perform the Analysis.",
    "noInstances": "No Instances in the current filter passed the selected Gateway.",
    "gatewayInstances": "Of all <b>{totalGateway} instances</b> that passed the Gateway <i>{gatewayName}</i>",
    "branchDistribution": "<b>{count}</b> ({branchPercentage}%) took the  <i>{key}</i> branch, <b>{reached}</b> ({reachedEndPercentage}%) of those then continued to reach the end event <i>{endEventName}</i>",
    "gatewayDistribution": "Distribution of Instances at the Gateway <i>{gatewayName}</i>:",
    "endEventProbability": "Probability to reach the end event <i>{endEventName}</i> after taking a branch:",
    "tooltip": {
      "totalInstances": "Process Instances Total",
      "reachedEnd": "Process Instances reached this state",
      "reachedEndPercentage": "of Process Instances reached this state"
    }
  },
  "common": {
    "name": "Name",
    "edit": "Edit",
    "editName": "Edit {name}",
    "delete": "Delete",
    "save": "Save",
    "apply": "Apply",
    "cancel": "Cancel",
    "add": "Add",
    "copy": "Copy",
    "copyName": "Copy {name}",
    "copyLabel": "copy",
    "saving": "Saving...",
    "creating": "Creating...",
    "select": "Select...",
    "selectWithoutEllipsis": "Select",
    "enableAll": "Enable All",
    "disableAll": "Disable All",
    "selectAll": "Select All",
    "deselectAll": "Deselect All",
    "and": "and",
    "off": "Off",
    "you": "You",
    "none": "None",
    "all": "All",
    "above": "above",
    "below": "below",
    "viewDetails": "View Details",
    "multiSelect": {
      "available": "Available items",
      "selected": "Selected items",
      "search": "Search for items",
      "empty": "No items found"
    },
    "entity": {
      "empty": "There are no {label} configured.",
      "create": {
        "Report": "Create a new Report...",
        "Dashboard": "Create a new Dashboard...",
        "Alert": "Create a new Alert"
      },
      "created": "Created",
      "changed": "Last changed",
      "modified": "Last modified",
      "by": "by",
      "showAll": "Show all...",
      "showLess": "Show less...",
      "namePlaceholder": {
        "Report": "Report name",
        "Dashboard": "dashboard name"
      }
    },
    "user": {
      "label": "User",
      "label-plural": "Users",
      "id": "User ID"
    },
    "user-group": {
      "label": "User Group",
      "label-plural": "User Groups",
      "id": "User Group ID"
    },
    "collection": {
      "label": "Collection",
      "label-plural": "Collections",
      "modal": {
        "title": {
          "new": "Create new Collection",
          "edit": "Edit Collection name"
        },
        "createBtn": "Create Collection",
        "editBtn": "Edit Collection",
        "inputLabel": "Add Name",
        "defaultName": "New Collection"
      }
    },
    "sharing": {
      "buttonTitle": "Share",
      "disabled": "Sharing is disabled per configuration",
      "popoverTitle": "Enable sharing",
      "link": {
        "title": "Link",
        "description": {
          "report": "Use the following URL to share the report with people who don't have a Camunda Optimize account:",
          "dashboard": "Use the following URL to share the dashboard with people who don't have a Camunda Optimize account:"
        }
      },
      "embed": {
        "title": "Embed",
        "description": {
          "report": "Use the following HTML code to embed the report into blogs and web pages:",
          "dashboard": "Use the following HTML code to embed the dashboard into blogs and web pages:"
        }
      }
    },
    "filter": {
      "types": {
        "running": "Running Instances Only",
        "completed": "Completed Instances Only",
        "canceled": "Canceled Instances Only",
        "nonCanceled": "Non Canceled Instances Only",
        "startDate": "Start Date",
        "endDate": "End Date",
        "duration": "Duration",
        "variable": "Variable",
        "flowNode": "Flow Node",
        "evaluationDateTime": "Evaluation Date Time",
        "inputVariable": "Input Variable",
        "outputVariable": "Output Variable"
      },
      "list": {
        "operators": {
          "between": "is between",
          "more": "is more than",
          "less": "is less than",
          "greater": "is greater than",
          "lessAgo": "is less than <span class='highlighted'>{duration}</span> ago",
          "is": "is",
          "not": "is not",
          "neither": "is neither",
          "nor": "nor",
          "or": "or"
        },
        "values": {
          "null": "null",
          "undefined": "undefined"
        },
        "running": "Running Process Instances Only",
        "completed": "Completed Process Instances Only",
        "canceled": "Canceled Process Instances Only",
        "nonCanceled": "Non Canceled Process Instances Only",
        "executedFlowNode": "Executed Flow Node"
      },
      "instanceCount": {
        "label": "{count} instance in current filter",
        "label-plural": "{count} instances in current filter"
      },
      "modalHeader": "Add {type} Filter",
      "addFilter": "Add Filter",
      "editFilter": "Edit Filter",
      "dateModal": {
        "endDateWarning": "Reports with an active End Date Filter will only show completed instances.",
        "fixedDate": "Fixed Date",
        "relativeDate": "Relative Date",
        "selectDates": "Select start and end dates to filter by:",
        "includeInstances": {
          "startDate": "Only include process instances started:",
          "endDate": "Only include process instances ended:",
          "evaluationDateTime": "Only include process instances evaluated:"
        },
        "inLast": "In the last",
        "invalidInput": "Please enter a numeric value",
        "buttons": {
          "today": "Today",
          "yesterday": "Yesterday",
          "past7": "Past 7 days",
          "past30": "Past 30 days",
          "lastWeek": "Last Week",
          "lastMonth": "Last Month",
          "lastYear": "Last Year",
          "thisWeek": "This Week",
          "thisMonth": "This Month",
          "thisYear": "This Year"
        },
        "to": "to",
        "invalidDate": "Please enter a valid date"
      },
      "variableModal": {
        "inputLabel": "Variable Name",
        "inputPlaceholder": "Select or search for a variable here",
        "noVariables": "No variables found",
        "loadMore": "Load More",
        "filterForUndefined": "Only display instances where variables are <b>null</b> or <b>undefined</b>.",
        "bool": {
          "isTrue": "is true",
          "isFalse": "is false"
        },
        "enterValue": "Enter value",
        "addValue": "Add Value",
        "multiSelect": {
          "available": "Available values",
          "selected": "Selected values",
          "search": "Search for values",
          "empty": "No values found"
        }
      },
      "durationModal": {
        "includeInstance": "Only include process instances that ran for...",
        "moreThan": "more than",
        "lessThan": "less than",
        "invalidInput": "Please enter a positive numeric value"
      },
      "nodeModal": {
        "executed": "was executed",
        "notExecuted": "was not executed",
        "previewLabel": "This is the filter you are about to create: "
      },
      "incompatibleFilters": "No data is shown since the combination of filters is incompatible with each other"
    },
    "definitionSelection": {
      "latest": "Latest",
      "multiple": "Multiple",
      "noDefinition": "No defintions found",
      "select": {
        "process": "Select Process",
        "decision": "Select Decision"
      },
      "version": {
        "label": "Version",
        "alwaysLatest": "Always display latest",
        "specific": {
          "label": "Specific version",
          "label-plural": "Specific versions"
        }
      },
      "tenant": {
        "label": "Tenant",
        "includeData": "Include data from"
      },
      "versionWarning": "Note: data from the older versions can deviate, therefore the report data can be inconsistent"
    },
    "confirmationModal": {
      "title": {
        "delete": "Delete {entityName}",
        "save": "Save {entityName}"
      },
      "description": {
        "label": "The following item will be affected by your action:",
        "label-plural": "The following items will be affected by your action:"
      },
      "affectedMessage": {
        "alerts": "\"{item}\" will be deleted from Alerts",
        "combined_report": "\"{item}\" will be removed from the Combined Report: \"{container}\"",
        "dashboard": "\"{item}\" will be removed from the Dashboard: \"{container}\"",
        "collection": "\"{item}\" will be removed from the Collection: \"{container}\""
      },
      "areYouSure": "Are you sure you want to proceed?"
    },
    "unit": {
      "milli": {
        "label": "millisecond",
        "label-plural": "milliseconds"
      },
      "second": {
        "label": "second",
        "label-plural": "seconds"
      },
      "minute": {
        "label": "minute",
        "label-plural": "minutes"
      },
      "hour": {
        "label": "hour",
        "label-plural": "hours"
      },
      "day": {
        "label": "day",
        "label-plural": "days"
      },
      "week": {
        "label": "week",
        "label-plural": "weeks"
      },
      "month": {
        "label": "month",
        "label-plural": "months"
      },
      "year": {
        "label": "year",
        "label-plural": "years"
      },
      "thousand": {
        "label": "thousand",
        "label-plural": "thousand"
      },
      "million": {
        "label": "million",
        "label-plural": "million"
      }
    }
  }
}
